{
    "version": "5.4.1",
    "flags": {},
    "shapes": [
        {
            "label": "osteochondroma",
            "points": [
                [
                    340.6152103297999,
                    285.27409342596553
                ],
                [
                    352.60036760030977,
                    298.8868646467916
                ]
            ],
            "group_id": null,
            "description": "",
            "shape_type": "rectangle",
            "flags": {},
            "mask": null
        },
        {
            "label": "osteochondroma",
            "points": [
                [
                    340.9458261607845,
                    292.99618069889834
                ],
                [
                    340.9458261607845,
                    291.13508278614245
                ],
                [
                    341.2781650737766,
                    288.37666980830795
                ],
                [
                    342.5742868344459,
                    286.5820396781505
                ],
                [
                    344.6015542036978,
                    286.1499990912607
                ],
                [
                    348.78902450739844,
                    286.28293465645766
                ],
                [
                    351.24833246354007,
                    287.27995139543395
                ],
                [
                    352.1456475286188,
                    290.8359777644496
                ],
                [
                    352.2121153112172,
                    293.4282212857881
                ],
                [
                    352.2121153112172,
                    294.7243430464573
                ],
                [
                    351.97947807212273,
                    296.2863359375203
                ],
                [
                    349.0216617464929,
                    296.18663426362264
                ],
                [
                    348.92196007259525,
                    296.88454598090607
                ],
                [
                    349.2210650942882,
                    298.2139016328746
                ],
                [
                    347.5926044206268,
                    298.3468371980714
                ],
                [
                    345.5321031600757,
                    297.34982045909504
                ]
            ],
            "group_id": null,
            "description": "",
            "shape_type": "polygon",
            "flags": {},
            "mask": null
        }
    ],
    "imagePath": "IMG000494.jpeg",
    "imageData": null,
    "imageHeight": 512,
    "imageWidth": 512
}