{
    "version": "5.4.1",
    "flags": {},
    "shapes": [
        {
            "label": "osteosarcoma",
            "points": [
                [
                    213.21130009076978,
                    134.8625507789831
                ],
                [
                    254.73325595583535,
                    188.19350326622325
                ]
            ],
            "group_id": null,
            "description": "",
            "shape_type": "rectangle",
            "flags": {},
            "mask": null
        },
        {
            "label": "osteosarcoma",
            "points": [
                [
                    214.8477388529088,
                    148.25629444371862
                ],
                [
                    221.69619316025558,
                    143.63756944574055
                ],
                [
                    225.35931988278992,
                    140.13370910244686
                ],
                [
                    234.59676987874604,
                    135.83351686295003
                ],
                [
                    250.20487504432708,
                    135.67425048370941
                ],
                [
                    253.70873538762078,
                    137.58544703459688
                ],
                [
                    253.70873538762078,
                    143.95610220422182
                ],
                [
                    251.31973969901145,
                    153.19355220017792
                ],
                [
                    253.70873538762078,
                    160.67907202448723
                ],
                [
                    253.8680017668614,
                    164.02366598854027
                ],
                [
                    250.36414142356767,
                    167.52752633183397
                ],
                [
                    248.29367849343961,
                    171.0313866751277
                ],
                [
                    248.61221125192085,
                    176.28717719006826
                ],
                [
                    248.134412114199,
                    182.49856598045255
                ],
                [
                    245.4268836671084,
                    186.79875821994938
                ],
                [
                    234.59676987874604,
                    186.79875821994938
                ],
                [
                    222.65179143569932,
                    186.79875821994938
                ],
                [
                    218.51086557544312,
                    184.88756166906188
                ],
                [
                    215.96260350759314,
                    177.0835090862714
                ],
                [
                    218.3515991962025,
                    171.34991943360896
                ],
                [
                    218.67013195468377,
                    168.1645918487965
                ],
                [
                    217.39600092075875,
                    164.18293236778092
                ],
                [
                    215.16627161139004,
                    160.99760478296847
                ],
                [
                    214.8477388529088,
                    153.6713513378998
                ]
            ],
            "group_id": null,
            "description": "",
            "shape_type": "polygon",
            "flags": {},
            "mask": null
        }
    ],
    "imagePath": "IMG000116.jpeg",
    "imageData": null,
    "imageHeight": 512,
    "imageWidth": 512
}