{
    "version": "5.4.1",
    "flags": {},
    "shapes": [
        {
            "label": "synovial osteochondroma",
            "points": [
                [
                    142.38141662153214,
                    219.41096467473068
                ],
                [
                    276.7979779743636,
                    320.3196726244208
                ]
            ],
            "group_id": null,
            "description": "",
            "shape_type": "rectangle",
            "flags": {},
            "mask": null
        },
        {
            "label": "synovial osteochondroma",
            "points": [
                [
                    144.6890112021002,
                    242.06226040781016
                ],
                [
                    145.6436509001954,
                    233.47050312495338
                ],
                [
                    149.08035381333812,
                    229.46101639295358
                ],
                [
                    157.67211109619487,
                    225.83338554019184
                ],
                [
                    159.58139049238525,
                    223.35132232514434
                ],
                [
                    163.39994928476602,
                    229.65194433257258
                ],
                [
                    165.1183007413374,
                    240.34390895123883
                ],
                [
                    167.21850807714682,
                    250.84494563028593
                ],
                [
                    173.51913008457512,
                    265.54639698095195
                ],
                [
                    192.0391402276219,
                    265.737324920571
                ],
                [
                    209.03172685371638,
                    259.62763085276174
                ],
                [
                    219.7236914723826,
                    242.44411628704822
                ],
                [
                    225.06967378171566,
                    231.561223728763
                ],
                [
                    230.22472815142976,
                    224.87874584209663
                ],
                [
                    234.9979266419057,
                    224.87874584209663
                ],
                [
                    240.34390895123883,
                    225.26060172133472
                ],
                [
                    242.82597216628633,
                    228.50637669485837
                ],
                [
                    248.36288241523843,
                    231.370295789144
                ],
                [
                    258.4820632150475,
                    246.6445309586671
                ],
                [
                    267.8375322563805,
                    260.58227055085695
                ],
                [
                    271.0833072299041,
                    266.31010873942813
                ],
                [
                    275.8565057203801,
                    273.94722632418967
                ],
                [
                    275.474649841142,
                    280.8206321504751
                ],
                [
                    272.22887486761834,
                    285.40290270133204
                ],
                [
                    261.15505436971404,
                    295.140227621903
                ],
                [
                    247.02638683790516,
                    301.4408496293313
                ],
                [
                    241.10762070971495,
                    312.5146701272356
                ],
                [
                    236.71627809847703,
                    313.66023776494984
                ],
                [
                    226.97895317790605,
                    316.5241568592354
                ],
                [
                    209.22265479333544,
                    316.9060127384735
                ],
                [
                    205.40409600095467,
                    310.6053907310452
                ],
                [
                    202.7311048462881,
                    304.49569666323595
                ],
                [
                    189.55707701257438,
                    296.85857907847435
                ],
                [
                    184.02016676362229,
                    295.140227621903
                ],
                [
                    179.8197520920034,
                    294.56744380304593
                ],
                [
                    175.4284094807655,
                    297.04950701809344
                ],
                [
                    167.0275801375278,
                    295.71301144076017
                ],
                [
                    162.06345370743276,
                    286.7393982786653
                ],
                [
                    154.23540818305216,
                    266.11918079980904
                ]
            ],
            "group_id": null,
            "description": "",
            "shape_type": "polygon",
            "flags": {},
            "mask": null
        }
    ],
    "imagePath": "IMG001191.jpeg",
    "imageData": null,
    "imageHeight": 512,
    "imageWidth": 512
}