{
    "version": "5.4.1",
    "flags": {},
    "shapes": [
        {
            "label": "osteochondroma",
            "points": [
                [
                    200.41581105461702,
                    190.39396424471053
                ],
                [
                    224.3488928981466,
                    219.57552894866328
                ]
            ],
            "group_id": null,
            "description": "",
            "shape_type": "rectangle",
            "flags": {},
            "mask": null
        },
        {
            "label": "osteochondroma",
            "points": [
                [
                    204.65558151190544,
                    217.02991020990663
                ],
                [
                    202.74187174542766,
                    214.94222682829448
                ],
                [
                    202.21995090002463,
                    210.7668600650702
                ],
                [
                    201.0891224016514,
                    205.98258564887573
                ],
                [
                    201.17610920921854,
                    201.54625846294988
                ],
                [
                    201.8720036697559,
                    197.1969180845913
                ],
                [
                    203.78571343623375,
                    192.84757770623264
                ],
                [
                    208.13505381459237,
                    191.020854747322
                ],
                [
                    210.5706844264732,
                    191.020854747322
                ],
                [
                    220.57416729669808,
                    191.10784155488918
                ],
                [
                    222.6618506783102,
                    193.89141939703873
                ],
                [
                    223.79267917668344,
                    198.6756938132332
                ],
                [
                    223.79267917668344,
                    205.0257307656368
                ],
                [
                    223.27075833128043,
                    211.89768856344344
                ],
                [
                    222.57486387074303,
                    215.11620044342882
                ],
                [
                    219.96525964372785,
                    218.07375190071272
                ],
                [
                    217.35565541671266,
                    218.85663316881727
                ],
                [
                    212.7453546156525,
                    218.94361997638444
                ],
                [
                    207.96108019945802,
                    218.94361997638444
                ]
            ],
            "group_id": null,
            "description": "",
            "shape_type": "polygon",
            "flags": {},
            "mask": null
        }
    ],
    "imagePath": "IMG000425.jpeg",
    "imageData": null,
    "imageHeight": 512,
    "imageWidth": 512
}