{
    "version": "5.4.1",
    "flags": {},
    "shapes": [
        {
            "label": "osteochondroma",
            "points": [
                [
                    202.0861903275367,
                    279.81818070526595
                ],
                [
                    215.24886913834158,
                    316.1722459922508
                ]
            ],
            "group_id": null,
            "description": "",
            "shape_type": "rectangle",
            "flags": {},
            "mask": null
        },
        {
            "label": "osteochondroma",
            "points": [
                [
                    203.21278611607153,
                    280.82906463499285
                ],
                [
                    214.0747439295917,
                    303.3966274708504
                ],
                [
                    211.0165227976297,
                    304.45118648187173
                ],
                [
                    210.80561099542544,
                    306.982128108323
                ],
                [
                    210.489243292119,
                    310.67308464689785
                ],
                [
                    209.8565078855062,
                    314.0476734821662
                ],
                [
                    206.4819190502378,
                    313.62584987775773
                ],
                [
                    204.05643332488864,
                    310.35671694359144
                ],
                [
                    203.21278611607153,
                    304.9784659873824
                ],
                [
                    203.10733021496938,
                    290.63646343749167
                ]
            ],
            "group_id": null,
            "description": "",
            "shape_type": "polygon",
            "flags": {},
            "mask": null
        }
    ],
    "imagePath": "IMG000858.jpeg",
    "imageData": null,
    "imageHeight": 512,
    "imageWidth": 512
}