{
    "version": "5.4.1",
    "flags": {},
    "shapes": [
        {
            "label": "osteochondroma",
            "points": [
                [
                    255.22159887798037,
                    245.71482000935015
                ],
                [
                    272.986909770921,
                    309.6699392239364
                ]
            ],
            "group_id": null,
            "description": "",
            "shape_type": "rectangle",
            "flags": {},
            "mask": null
        },
        {
            "label": "osteochondroma",
            "points": [
                [
                    266.82377837629855,
                    308.426317814544
                ],
                [
                    271.0561754520969,
                    302.5009619084263
                ],
                [
                    271.5178914967295,
                    288.95729126587145
                ],
                [
                    269.20931127356675,
                    247.17198922662558
                ],
                [
                    264.13043478260863,
                    247.24894190073104
                ],
                [
                    262.43747595228933,
                    251.55829165063483
                ],
                [
                    261.2062331666025,
                    255.02116198537897
                ],
                [
                    260.0519430550211,
                    259.4074644093882
                ],
                [
                    258.58984224701805,
                    260.33089649865326
                ],
                [
                    257.666410157753,
                    259.1766063870719
                ],
                [
                    256.4351673720662,
                    263.3320507887649
                ],
                [
                    256.35821469796076,
                    267.7183532127741
                ],
                [
                    256.35821469796076,
                    270.5656021546749
                ],
                [
                    257.127741439015,
                    274.87495190457867
                ],
                [
                    262.74528664871104,
                    294.4978838014621
                ],
                [
                    263.2070026933436,
                    299.8076183147364
                ],
                [
                    264.05348210850326,
                    304.80954213158907
                ]
            ],
            "group_id": null,
            "description": "",
            "shape_type": "polygon",
            "flags": {},
            "mask": null
        }
    ],
    "imagePath": "IMG000900.jpeg",
    "imageData": null,
    "imageHeight": 512,
    "imageWidth": 512
}