{
    "version": "5.4.1",
    "flags": {},
    "shapes": [
        {
            "label": "other bt",
            "points": [
                [
                    287.7826947280794,
                    58.68979938358268
                ],
                [
                    324.9923658070078,
                    121.60797048067997
                ]
            ],
            "group_id": null,
            "description": "",
            "shape_type": "rectangle",
            "flags": {},
            "mask": null
        },
        {
            "label": "other bt",
            "points": [
                [
                    294.475422316111,
                    69.43290552994827
                ],
                [
                    295.35273339681436,
                    64.29436920011456
                ],
                [
                    297.35801586699336,
                    59.90781379659797
                ],
                [
                    304.50183466700605,
                    59.406493179053214
                ],
                [
                    310.7683423863155,
                    60.91045503168747
                ],
                [
                    318.0374913407144,
                    66.04899136152119
                ],
                [
                    322.9253673617757,
                    74.82210216855437
                ],
                [
                    323.5520181337067,
                    84.47252405629085
                ],
                [
                    323.17602767054814,
                    98.00818072999918
                ],
                [
                    321.42140550914144,
                    105.02666937562572
                ],
                [
                    313.5256057828116,
                    115.42907218967935
                ],
                [
                    303.2485331231442,
                    120.06628790196831
                ],
                [
                    298.3606571020829,
                    120.31694821074068
                ],
                [
                    292.9714604634768,
                    120.56760851951304
                ],
                [
                    290.21419706698066,
                    117.30902450547217
                ],
                [
                    289.4622161406635,
                    109.5385549335285
                ],
                [
                    289.5875462950497,
                    100.26412350895056
                ],
                [
                    290.0888669125944,
                    88.60841915103506
                ],
                [
                    294.35009216172483,
                    70.68620707381015
                ]
            ],
            "group_id": null,
            "description": "",
            "shape_type": "polygon",
            "flags": {},
            "mask": null
        }
    ],
    "imagePath": "IMG000845.jpeg",
    "imageData": null,
    "imageHeight": 512,
    "imageWidth": 512
}