{
    "version": "5.4.1",
    "flags": {},
    "shapes": [
        {
            "label": "giant cell tumor",
            "points": [
                [
                    216.93241769975162,
                    188.88750519820616
                ],
                [
                    300.22959774313557,
                    284.2692502219774
                ]
            ],
            "group_id": null,
            "description": "",
            "shape_type": "rectangle",
            "flags": {},
            "mask": null
        },
        {
            "label": "giant cell tumor",
            "points": [
                [
                    218.51492025670711,
                    195.79297090128466
                ],
                [
                    225.1326582221573,
                    190.90159936160407
                ],
                [
                    227.72220786081172,
                    190.1822800175334
                ],
                [
                    242.2524586110393,
                    192.7718296561878
                ],
                [
                    258.6529396558507,
                    192.19637418093126
                ],
                [
                    264.69522214604433,
                    192.62796578737368
                ],
                [
                    273.1831904060782,
                    199.389567621638
                ],
                [
                    278.6500174210154,
                    213.77595450305148
                ],
                [
                    284.5484360423949,
                    218.81118991154617
                ],
                [
                    288.4327605003765,
                    223.99028918885503
                ],
                [
                    293.180268171243,
                    234.34848774347273
                ],
                [
                    293.7557236464995,
                    237.65735672619783
                ],
                [
                    297.20845649803874,
                    241.68554505299358
                ],
                [
                    299.0786867926225,
                    247.1523720679307
                ],
                [
                    298.6470951861801,
                    254.3455655086374
                ],
                [
                    293.61185977768537,
                    263.6967169815562
                ],
                [
                    286.1309385993504,
                    270.4583188158205
                ],
                [
                    278.2184258145729,
                    278.3708316005979
                ],
                [
                    272.0322794555652,
                    280.52878963280995
                ],
                [
                    270.30591302979553,
                    282.8306115338361
                ],
                [
                    263.4004473267171,
                    282.11129218976544
                ],
                [
                    255.4879345419397,
                    280.09719802636755
                ],
                [
                    244.41041664325132,
                    275.06196261787284
                ],
                [
                    232.90130713812053,
                    269.882863340564
                ],
                [
                    227.86607172962584,
                    263.8405808503703
                ],
                [
                    226.71516077911275,
                    248.44714688725793
                ],
                [
                    224.84493048452904,
                    237.65735672619783
                ],
                [
                    226.57129691029863,
                    226.57983882750946
                ],
                [
                    223.5501556652018,
                    211.90572420846772
                ],
                [
                    219.8096950760343,
                    197.95092893349667
                ]
            ],
            "group_id": null,
            "description": "",
            "shape_type": "polygon",
            "flags": {},
            "mask": null
        }
    ],
    "imagePath": "IMG000812.jpeg",
    "imageData": null,
    "imageHeight": 512,
    "imageWidth": 512
}