{
    "version": "5.4.1",
    "flags": {},
    "shapes": [
        {
            "label": "osteosarcoma",
            "points": [
                [
                    222.08762169680114,
                    369.08150208623084
                ],
                [
                    284.75243393602227,
                    437.4431154381084
                ]
            ],
            "group_id": null,
            "description": "",
            "shape_type": "rectangle",
            "flags": {},
            "mask": null
        },
        {
            "label": "osteosarcoma",
            "points": [
                [
                    237.26844708333073,
                    436.34015854107287
                ],
                [
                    225.45333266806787,
                    431.39058358332755
                ],
                [
                    223.53736816829553,
                    420.37378770963653
                ],
                [
                    223.37770445998115,
                    411.751947460661
                ],
                [
                    223.37770445998115,
                    400.4158241703412
                ],
                [
                    223.37770445998115,
                    392.75196617125175
                ],
                [
                    224.81467783481042,
                    382.8528162557613
                ],
                [
                    229.44492537592697,
                    375.66794938161496
                ],
                [
                    237.10878337501634,
                    371.8360203820703
                ],
                [
                    242.69701316601908,
                    371.19736554881274
                ],
                [
                    254.35246387296758,
                    369.7603921739835
                ],
                [
                    269.520516162832,
                    369.92005588229785
                ],
                [
                    277.34403787023587,
                    371.19736554881274
                ],
                [
                    281.1759668697805,
                    377.2645864647586
                ],
                [
                    283.09193136955287,
                    386.52508154699166
                ],
                [
                    283.41125878618163,
                    395.6259129209103
                ],
                [
                    283.41125878618163,
                    406.16371766965824
                ],
                [
                    283.89024991112467,
                    411.9116111689753
                ],
                [
                    283.89024991112467,
                    418.61748691817854
                ],
                [
                    283.41125878618163,
                    429.1552916669265
                ],
                [
                    283.41125878618163,
                    433.4662117914143
                ],
                [
                    278.302020120122,
                    437.13847708264467
                ]
            ],
            "group_id": null,
            "description": "",
            "shape_type": "polygon",
            "flags": {},
            "mask": null
        }
    ],
    "imagePath": "IMG000067.jpeg",
    "imageData": null,
    "imageHeight": 512,
    "imageWidth": 512
}